coloriseq/__init__.py
coloriseq/__main__.py
coloriseq-0.1.1.dist-info/METADATA
coloriseq-0.1.1.dist-info/WHEEL
coloriseq-0.1.1.dist-info/entry_points.txt
coloriseq-0.1.1.dist-info/RECORD
